terminal_menu.py
terminal_menu-0.0.0.dist-info/LICENSE
terminal_menu-0.0.0.dist-info/METADATA
terminal_menu-0.0.0.dist-info/WHEEL
terminal_menu-0.0.0.dist-info/top_level.txt
terminal_menu-0.0.0.dist-info/RECORD
