Metadata-Version: 2.1
Name: terminal-menu
Version: 0.0.0
Summary: Tool for creating menus in terminal (using on the python standard library)
Author-email: Joseph Bolton <joseph.jazz.bolton@gmail.com>
License: GNU GENERAL PUBLIC LICENSE
Project-URL: Homepage, https://github.com/J-sephB-lt-n/terminal-menu
Keywords: terminal,menu,curses
Classifier: License :: OSI Approved :: GNU General Public License v3 (GPLv3)
Classifier: Programming Language :: Python
Classifier: Programming Language :: Python :: 3
Requires-Python: >=3.6
License-File: LICENSE
Provides-Extra: build
Requires-Dist: build ; extra == 'build'
Requires-Dist: twine ; extra == 'build'
